treetools/__init__.py
treetools/cli.py
treetools/grammar.py
treetools/grammaranalysis.py
treetools/grammarconst.py
treetools/grammarinput.py
treetools/grammaroutput.py
treetools/misc.py
treetools/transform.py
treetools/transformconst.py
treetools/transitionoutput.py
treetools/transitions.py
treetools/treeanalysis.py
treetools/treeinput.py
treetools/treeoutput.py
treetools/trees.py
treetools-1.0.0.dist-info/licenses/LICENSE
treetools-1.0.0.dist-info/METADATA
treetools-1.0.0.dist-info/WHEEL
treetools-1.0.0.dist-info/entry_points.txt
treetools-1.0.0.dist-info/top_level.txt
treetools-1.0.0.dist-info/RECORD
