Metadata-Version: 2.4
Name: treetools
Version: 1.0.0
Summary: Tools for processing treebank trees
Author-email: Wolfgang Maier <maierw@hhu.de>
License-Expression: GPL-3.0-or-later
Project-URL: Homepage, https://github.com/wmaier/treetools
Project-URL: Repository, https://github.com/wmaier/treetools
Project-URL: Issues, https://github.com/wmaier/treetools/issues
Project-URL: Download, https://github.com/wmaier/treetools/archive/v1.0.0.tar.gz
Project-URL: Changelog, https://github.com/wmaier/treetools/releases
Keywords: treebanks,trees,grammar
Classifier: Development Status :: 4 - Beta
Classifier: Environment :: Console
Classifier: Intended Audience :: Science/Research
Classifier: Operating System :: OS Independent
Classifier: Programming Language :: Python
Classifier: Programming Language :: Python :: 3
Classifier: Programming Language :: Python :: 3 :: Only
Classifier: Programming Language :: Python :: 3.11
Classifier: Programming Language :: Python :: 3.12
Classifier: Topic :: Text Processing :: Linguistic
Requires-Python: >=3.11
License-File: LICENSE
Provides-Extra: dev
Requires-Dist: pytest>=7; extra == "dev"
Requires-Dist: pytest-cov>=4; extra == "dev"
Dynamic: license-file
